daikin_altherma/__init__.py
python_daikin_altherma-0.5.0.dist-info/METADATA
python_daikin_altherma-0.5.0.dist-info/WHEEL
python_daikin_altherma-0.5.0.dist-info/top_level.txt
python_daikin_altherma-0.5.0.dist-info/RECORD
