Metadata-Version: 2.4
Name: python-daikin-altherma
Version: 0.5.0
Summary: Connect to daikin altherma heat pumps
Home-page: http://github.com/Frankkkkk/python-daikin-altherma
Author: Frank Villaro-Dixon
Author-email: frank@villaro-dixon.eu
License: MIT
Keywords: daikin altherma heat pump
Classifier: Development Status :: 3 - Alpha
Classifier: Topic :: Utilities
Classifier: License :: OSI Approved :: MIT License
Requires-Dist: websocket-client
Requires-Dist: dpath
Dynamic: author
Dynamic: author-email
Dynamic: classifier
Dynamic: description
Dynamic: description-content-type
Dynamic: home-page
Dynamic: keywords
Dynamic: license
Dynamic: requires-dist
Dynamic: summary
